gllvm/__init__.py
gllvm/decoder.py
gllvm/encoder.py
gllvm/estimator.py
gllvm/families.py
gllvm/gllvm.py
gllvm/glms.py
gllvm/utils.py
gllvm-0.1.0.dist-info/licenses/LICENSE
gllvm-0.1.0.dist-info/METADATA
gllvm-0.1.0.dist-info/WHEEL
gllvm-0.1.0.dist-info/top_level.txt
gllvm-0.1.0.dist-info/RECORD
