Metadata-Version: 2.4
Name: gllvm
Version: 0.1.0
Summary: Generalized latent variable model framework.
License: MIT
Project-URL: Homepage, https://github.com/wiwh/gllvm
Project-URL: Repository, https://github.com/wiwh/gllvm
Project-URL: Issues, https://github.com/wiwh/gllvm/issues
Requires-Python: >=3.10
License-File: LICENSE
Requires-Dist: torch>=1.8.0
Dynamic: license-file
